CHANGELOG.txt
MANIFEST.in
README.md
setup.py
FireNext/NextDatabase.py
FireNext/NextTable.py
FireNext/__init__.py
FireNext/Doc/__init__.py
FireNext/Doc/__self__.py
FireNext/Doc/__self__add__.py
FireNext/Doc/__self__check__.py
FireNext/Doc/__self__child__.py
FireNext/Doc/__self__child__delete__.py
FireNext/Doc/__self__delete__.py
FireNext/Doc/__self__query__.py
FireNext/Doc/__self__read__.py
FireNext/Doc/__self__update__.py
FireNext/Doc/__tag__.py
FireNext/Table/__add__col__name__.py
FireNext/Table/__add__data__.py
FireNext/Table/__character__count__.py
FireNext/Table/__convert__table__doc__.py
FireNext/Table/__create__table__.py
FireNext/Table/__delete__col__.py
FireNext/Table/__delete__col__name__.py
FireNext/Table/__delete__data__.py
FireNext/Table/__delete__row__.py
FireNext/Table/__delete__table__.py
FireNext/Table/__init__.py
FireNext/Table/__parent__update__.py
FireNext/Table/__read__col__name__.py
FireNext/Table/__read__table__.py
FireNext/Table/__search__col__data__.py
FireNext/Table/__search__data__.py
FireNext/Table/__search__row__data__.py
FireNext/Table/__tag__.py
FireNext/Table/__update__col__data__.py
FireNext/Table/__update__data__.py
FireNext/Table/__update__row__.py
firenext.egg-info/PKG-INFO
firenext.egg-info/SOURCES.txt
firenext.egg-info/dependency_links.txt
firenext.egg-info/top_level.txt
venv/Lib/site-packages/_virtualenv.py
venv/Lib/site-packages/_distutils_hack/__init__.py
venv/Lib/site-packages/_distutils_hack/override.py
venv/Lib/site-packages/pip/__init__.py
venv/Lib/site-packages/pip/__main__.py
venv/Lib/site-packages/pip-21.3.1.dist-info/LICENSE.txt
venv/Lib/site-packages/pip-21.3.1.dist-info/entry_points.txt
venv/Lib/site-packages/pip-21.3.1.dist-info/top_level.txt
venv/Lib/site-packages/pip/_internal/__init__.py
venv/Lib/site-packages/pip/_internal/build_env.py
venv/Lib/site-packages/pip/_internal/cache.py
venv/Lib/site-packages/pip/_internal/configuration.py
venv/Lib/site-packages/pip/_internal/exceptions.py
venv/Lib/site-packages/pip/_internal/main.py
venv/Lib/site-packages/pip/_internal/pyproject.py
venv/Lib/site-packages/pip/_internal/self_outdated_check.py
venv/Lib/site-packages/pip/_internal/wheel_builder.py
venv/Lib/site-packages/pip/_internal/cli/__init__.py
venv/Lib/site-packages/pip/_internal/cli/autocompletion.py
venv/Lib/site-packages/setuptools-60.2.0.dist-info/entry_points.txt
venv/Lib/site-packages/setuptools-60.2.0.dist-info/top_level.txt
venv/Lib/site-packages/wheel-0.37.1.dist-info/LICENSE.txt
venv/Lib/site-packages/wheel-0.37.1.dist-info/entry_points.txt
venv/Lib/site-packages/wheel-0.37.1.dist-info/top_level.txt
