Metadata-Version: 2.1
Name: firenext
Version: 1.2.0
Summary: This is an offline database library.
Home-page: https://github.com/almoaz/PyFireNext
Author: Mahfuz Salehin Moaz
Author-email: almuaz1998@gmail.com
License: MIT
Keywords: firenext
Platform: UNKNOWN
Classifier: Development Status :: 5 - Production/Stable
Classifier: Intended Audience :: Developers
Classifier: License :: OSI Approved :: MIT License
Classifier: Programming Language :: Python :: 3.6
Classifier: Programming Language :: Python :: 3.7
Classifier: Programming Language :: Python :: 3.8
Classifier: Programming Language :: Python :: 3.9
Classifier: Programming Language :: Python :: 3.10
Classifier: Programming Language :: Python :: 3.11
Classifier: Programming Language :: Python :: 3.12
